[
  {
    "name": "kodom",
    "photo": "kichu ekta",
    "price": 45,
    "info": "info dibo"
  },
  {
    "name": "kodom",
    "photo": "kichu ekta",
    "price": 45,
    "info": "info dibo"
  },
  {
    "name": "kodom",
    "photo": "kichu ekta",
    "price": 45,
    "info": "info dibo"
  },
  {
    "name": "kodom",
    "photo": "kichu ekta",
    "price": 45,
    "info": "info dibo"
  },
  {
    "name": "kodom",
    "photo": "kichu ekta",
    "price": 45,
    "info": "info dibo"
  },
  {
    "name": "kodom",
    "photo": "kichu ekta",
    "price": 45,
    "info": "info dibo"
  }
]
